gpubs
